jupyterlab4_stan_highlight/__init__.py
jupyterlab4_stan_highlight/_version.py
jupyterlab4_stan_highlight-0.4.0.data/data/share/jupyter/labextensions/jupyterlab-stan-highlight/build_log.json
jupyterlab4_stan_highlight-0.4.0.data/data/share/jupyter/labextensions/jupyterlab-stan-highlight/package.json
jupyterlab4_stan_highlight-0.4.0.data/data/share/jupyter/labextensions/jupyterlab-stan-highlight/install.json
jupyterlab4_stan_highlight-0.4.0.dist-info/METADATA
jupyterlab4_stan_highlight-0.4.0.dist-info/WHEEL
jupyterlab4_stan_highlight-0.4.0.dist-info/licenses/LICENSE
jupyterlab4_stan_highlight-0.4.0.dist-info/RECORD
